GrnGame/__init__.py
GrnGame/chargerlib.py
GrnGame/chemin.py
GrnGame/compilation.py
GrnGame/installation.py
GrnGame/renvoielib.py
GrnGame/signatures.py
GrnGame/structures.py
GrnGame/systeme.py
GrnGame/creations/example/License.txt
GrnGame/creations/example/example.gif
GrnGame/creations/example/main.py
GrnGame/creations/example/assets/1.png
GrnGame/creations/example/assets/10.png
GrnGame/creations/example/assets/11.png
GrnGame/creations/example/assets/12.png
GrnGame/creations/example/assets/13.png
GrnGame/creations/example/assets/14.png
GrnGame/creations/example/assets/15.png
GrnGame/creations/example/assets/16.png
GrnGame/creations/example/assets/17.png
GrnGame/creations/example/assets/18.png
GrnGame/creations/example/assets/19.png
GrnGame/creations/example/assets/2.png
GrnGame/creations/example/assets/20.png
GrnGame/creations/example/assets/21.png
GrnGame/creations/example/assets/22.png
GrnGame/creations/example/assets/23.png
GrnGame/creations/example/assets/24.png
GrnGame/creations/example/assets/25.png
GrnGame/creations/example/assets/26.png
GrnGame/creations/example/assets/27.png
GrnGame/creations/example/assets/28.png
GrnGame/creations/example/assets/29.png
GrnGame/creations/example/assets/3.png
GrnGame/creations/example/assets/30.png
GrnGame/creations/example/assets/31.png
GrnGame/creations/example/assets/32.png
GrnGame/creations/example/assets/33.png
GrnGame/creations/example/assets/4.png
GrnGame/creations/example/assets/5.png
GrnGame/creations/example/assets/6.png
GrnGame/creations/example/assets/7.png
GrnGame/creations/example/assets/8.png
GrnGame/creations/example/assets/9.png
GrnGame/creations/example/assets/fond.png
GrnGame/creations/example/assets/police/100.png
GrnGame/creations/example/assets/police/101.png
GrnGame/creations/example/assets/police/102.png
GrnGame/creations/example/assets/police/103.png
GrnGame/creations/example/assets/police/104.png
GrnGame/creations/example/assets/police/105.png
GrnGame/creations/example/assets/police/106.png
grngame-1.1.1.dist-info/METADATA
grngame-1.1.1.dist-info/WHEEL
grngame-1.1.1.dist-info/entry_points.txt
grngame-1.1.1.dist-info/top_level.txt
grngame-1.1.1.dist-info/RECORD
